technicators/__init__.py
technicators/__technicators__.py
technicators-1.0.1.dist-info/LICENSE
technicators-1.0.1.dist-info/METADATA
technicators-1.0.1.dist-info/WHEEL
technicators-1.0.1.dist-info/RECORD
