Metadata-Version: 2.1
Name: technicators
Version: 1.0.1
Summary: Library for calculating diverse financial metrics
Home-page: https://github.com/Tejaromalius/Technicators
License: MIT
Keywords: market,analyze,indicator
Author: tejaromalius
Author-email: tayefi.ilia@protonmail.com
Requires-Python: >=3.9,<4.0
Classifier: Development Status :: 4 - Beta
Classifier: Intended Audience :: Science/Research
Classifier: License :: OSI Approved :: MIT License
Classifier: Natural Language :: English
Classifier: Operating System :: OS Independent
Classifier: Programming Language :: Python :: 3
Classifier: Programming Language :: Python :: 3.9
Classifier: Programming Language :: Python :: 3.10
Classifier: Programming Language :: Python :: 3.11
Classifier: Programming Language :: Python :: 3.12
Classifier: Topic :: Software Development :: Libraries
Requires-Dist: numpy (>=1.26.3,<2.0.0)
Requires-Dist: pandas (>=2.2.0,<3.0.0)
Requires-Dist: pyarrow (>=15.0.0,<16.0.0)
Project-URL: Repository, https://github.com/Tejaromalius/Technicators
